{
    "formatVersion": 1,
    "passTypeIdentifier": "pass.com.runx.wallet",
    "serialNumber": "12345678",
    "teamIdentifier": "TEAMID123",
    "organizationName": "RunX",
    "description": "RunX Pass",
    "foregroundColor": "rgb(255, 255, 255)",
    "backgroundColor": "rgb(51, 51, 51)",
    "labelColor": "rgb(255, 255, 255)",
    "storeCard": {
        "headerFields": [],
        "primaryFields": [
            {
                "key": "name",
                "label": "Name",
                "value": "Jane Doe"
            }
        ],
        "secondaryFields": [
            {
                "key": "email",
                "label": "Account",
                "value": "person@sunrun.com"
            }
        ],
        "auxiliaryFields": [],
        "backFields": []
    },
    "barcode": {
        "format": "PKBarcodeFormatQR",
        "message": "123456789",
        "messageEncoding": "iso-8859-1",
        "altText": "123456789"
    }
}
